__init__.py
setup.py
PyDirDuplicateFinder.egg-info/PKG-INFO
PyDirDuplicateFinder.egg-info/SOURCES.txt
PyDirDuplicateFinder.egg-info/dependency_links.txt
PyDirDuplicateFinder.egg-info/entry_points.txt
PyDirDuplicateFinder.egg-info/not-zip-safe
PyDirDuplicateFinder.egg-info/top_level.txt
docs/HISTORY.txt
docs/README.txt
pydirduplicatefinder/__init__.py
pydirduplicatefinder/duplicatefinder.py
pydirduplicatefinder/filters.py
pydirduplicatefinder/interface_texts.py
pydirduplicatefinder/raw_input_defaulted.py
pydirduplicatefinder/tests/__init__.py
pydirduplicatefinder/tests/test_filters.py
pydirduplicatefinder/tests/test_functions.py
pydirduplicatefinder/tests/testcase.py