Metadata-Version: 1.0
Name: PyDirDuplicateFinder
Version: 0.3.0
Summary: Analyse all files in one or more directories and manage duplicate files (the same file present with different names)
Home-page: http://keul.it/develop/python/pydirduplicatefinder/
Author: Keul
Author-email: luca@keul.it
License: GPL
Keywords: filesystem file duplicate directory utility
Platform: UNKNOWN
Classifier: Development Status :: 4 - Beta
Classifier: Intended Audience :: End Users/Desktop
Classifier: License :: OSI Approved :: GNU General Public License (GPL)
Classifier: Operating System :: OS Independent
Classifier: Programming Language :: Python :: 2.5
Classifier: Topic :: Desktop Environment :: File Managers
Classifier: Topic :: Utilities
